klarfio/__init__.py
klarfio/example.py
klarfio/klarfio.py
klarfio/test.py
klarfio-0.9.1.dist-info/LICENSE
klarfio-0.9.1.dist-info/METADATA
klarfio-0.9.1.dist-info/WHEEL
klarfio-0.9.1.dist-info/top_level.txt
klarfio-0.9.1.dist-info/RECORD
